LICENSE
README.rst
setup.py
pfdo_med2image/__init__.py
pfdo_med2image/__main__.py
pfdo_med2image/pfdo_med2image.py
pfdo_med2image.egg-info/PKG-INFO
pfdo_med2image.egg-info/SOURCES.txt
pfdo_med2image.egg-info/dependency_links.txt
pfdo_med2image.egg-info/entry_points.txt
pfdo_med2image.egg-info/not-zip-safe
pfdo_med2image.egg-info/requires.txt
pfdo_med2image.egg-info/top_level.txt