Metadata-Version: 2.1
Name: pfdo-med2image
Version: 2.0.4
Summary: Runs med2image on each nested dir of an inputdir
Home-page: https://github.com/FNNDSC/pfdo_med2image
Author: FNNDSC
Author-email: dev@babymri.org
License: MIT
Platform: UNKNOWN
License-File: LICENSE
